delfick_logging.py
delfick_logging-0.1.dist-info/DESCRIPTION.rst
delfick_logging-0.1.dist-info/METADATA
delfick_logging-0.1.dist-info/RECORD
delfick_logging-0.1.dist-info/WHEEL
delfick_logging-0.1.dist-info/metadata.json
delfick_logging-0.1.dist-info/top_level.txt
